logsight_cli_py-0.0.2.data/scripts/logsight
src/__init__.py
src/ls-cli.py
src/application/__init__.py
src/application/application.py
src/compare/__init__.py
src/compare/compare.py
src/incident/__init__.py
src/incident/incident.py
src/log/__init__.py
src/log/log.py
src/transformation/__init__.py
src/transformation/log_parser.py
src/transformation/transformation.py
logsight_cli_py-0.0.2.dist-info/LICENSE
logsight_cli_py-0.0.2.dist-info/METADATA
logsight_cli_py-0.0.2.dist-info/WHEEL
logsight_cli_py-0.0.2.dist-info/top_level.txt
logsight_cli_py-0.0.2.dist-info/RECORD
