Metadata-Version: 2.1
Name: logsight-cli-py
Version: 0.0.2
Summary: Logsight CLI Python
Home-page: https://github.com/aiops/logsight-cli-py
Author: Jorge Cardoso
Author-email: jorge.cardoso.pt@gmail.com
License: unlicense
Project-URL: Documentation, http://logsight.readthedocs.io/en/latest/
Project-URL: Source, https://github.com/aiops/logsight-cli-py
Project-URL: Tracker, https://github.com/aiops/logsight-cli-py/issues
Platform: UNKNOWN
Classifier: Development Status :: 3 - Alpha
Classifier: Programming Language :: Python :: 3.6
Classifier: Programming Language :: Python :: 3.7
Classifier: Programming Language :: Python :: 3.8
Classifier: Programming Language :: Python :: 3.9
Classifier: Operating System :: OS Independent
Classifier: Topic :: Utilities
Requires-Python: >=3.6
License-File: LICENSE
Requires-Dist: logsight-sdk-py
Requires-Dist: click
Requires-Dist: prettytable
Requires-Dist: tqdm
